git_vanity-0.3.data/scripts/git-vanity
git_vanity-0.3.dist-info/METADATA
git_vanity-0.3.dist-info/RECORD
git_vanity-0.3.dist-info/WHEEL
git_vanity-0.3.dist-info/top_level.txt
gitvanity/__init__.py
gitvanity/bad-words-en.csv
gitvanity/templates/base.html
gitvanity/templates/index.html
gitvanity/templates/metric.html
