Metadata-Version: 2.1
Name: git-vanity
Version: 0.3
Summary: vanity leaderboard for git
Home-page: http://github.com/intuition-app/frontend
Author: Brian Brunner
Author-email: brian@intuition.app
License: MIT
Platform: UNKNOWN
Requires-Dist: Click (==7.0)
Requires-Dist: GitPython (==2.1.11)
Requires-Dist: Jinja2 (==2.10)
